neverwhere/__init__.py
neverwhere/types.py
neverwhere-0.0.1rc1.dist-info/LICENSE
neverwhere-0.0.1rc1.dist-info/METADATA
neverwhere-0.0.1rc1.dist-info/WHEEL
neverwhere-0.0.1rc1.dist-info/entry_points.txt
neverwhere-0.0.1rc1.dist-info/top_level.txt
neverwhere-0.0.1rc1.dist-info/RECORD
