Metadata-Version: 2.1
Name: neverwhere
Version: 0.0.1rc1
Home-page: https://github.com/embodied-intelligence/neverwhere
Author: Ge Yang<ge.ike.yang@gmail.com>
Author-email: ge.ike.yang@gmail.com
License: MIT
Classifier: Development Status :: 3 - Alpha
Classifier: Programming Language :: Python
Requires-Python: >=3.7
License-File: LICENSE
Requires-Dist: params-proto >=2.11.16
Requires-Dist: pillow
Requires-Dist: msgpack
Requires-Dist: numpy >=1.21
Requires-Dist: websockets
Provides-Extra: all
Requires-Dist: aiohttp ; extra == 'all'
Requires-Dist: aiohttp-cors ; extra == 'all'
Requires-Dist: killport ; extra == 'all'
Provides-Extra: dev
Requires-Dist: aiohttp ; extra == 'dev'
Requires-Dist: aiohttp-cors ; extra == 'dev'
Requires-Dist: killport ; extra == 'dev'
Requires-Dist: black ==22.3.0 ; extra == 'dev'
Requires-Dist: pylint ==2.13.4 ; extra == 'dev'
Requires-Dist: pytest ==7.1.2 ; extra == 'dev'
Requires-Dist: sphinx ==7.1.2 ; extra == 'dev'
Requires-Dist: furo ; extra == 'dev'
Requires-Dist: sphinx-copybutton ; extra == 'dev'
Requires-Dist: myst-parser ; extra == 'dev'
Requires-Dist: trimesh ; extra == 'dev'
Requires-Dist: tqdm ; extra == 'dev'
Provides-Extra: example
Requires-Dist: aiohttp ; extra == 'example'
Requires-Dist: aiohttp-cors ; extra == 'example'
Requires-Dist: killport ; extra == 'example'
Requires-Dist: open3d <0.16.0,>=0.15.0 ; extra == 'example'
Requires-Dist: trimesh ; extra == 'example'
Requires-Dist: cmx ; extra == 'example'
Requires-Dist: functional-notations ; extra == 'example'
Requires-Dist: ml-logger ; extra == 'example'
Requires-Dist: opencv-python ; extra == 'example'
